nonebot_desktop_tk/__init__.py
nonebot_desktop_tk/__main__.py
nonebot_desktop_tk/gui.py
nonebot_desktop_tk-1.0.6.dist-info/LICENSE
nonebot_desktop_tk-1.0.6.dist-info/METADATA
nonebot_desktop_tk-1.0.6.dist-info/WHEEL
nonebot_desktop_tk-1.0.6.dist-info/top_level.txt
nonebot_desktop_tk-1.0.6.dist-info/RECORD
