Metadata-Version: 2.1
Name: nonebot-desktop-tk
Version: 1.0.6
Summary: NoneBot2 GUI manager written with tkinter.
Author-email: HivertMoZara <worldmozara@163.com>
License: MIT
Project-URL: Homepage, https://github.com/nonedesktop/nonebot-desktop-tk
Project-URL: Repository, https://github.com/nonedesktop/nonebot-desktop-tk
Requires-Python: >=3.8
License-File: LICENSE
Requires-Dist: tkreform (>=0.3.6)
Requires-Dist: nonebot-desktop-wing (>=0.2.8)
